pyrocks/__init__.py
pyrocks/pyrocks.py
pyrocks-0.0.1b0.dist-info/LICENSE
pyrocks-0.0.1b0.dist-info/METADATA
pyrocks-0.0.1b0.dist-info/WHEEL
pyrocks-0.0.1b0.dist-info/top_level.txt
pyrocks-0.0.1b0.dist-info/RECORD
