Metadata-Version: 2.1
Name: pyrocks
Version: 0.0.1b0
Summary: Python bindings for RocksDB
Home-page: 
Author: Rodrigo Martínez (brunneis)
Author-email: dev@brunneis.com
License: BSD 3-Clause "New" or "Revised" License (BSD-3-Clause)
Classifier: Development Status :: 4 - Beta
Classifier: Environment :: Console
Classifier: Intended Audience :: Developers
Classifier: License :: OSI Approved :: BSD License
Classifier: Operating System :: POSIX :: Linux
Classifier: Programming Language :: Python :: 3.10
Classifier: Programming Language :: Python :: Implementation :: PyPy
Classifier: Topic :: Software Development :: Libraries :: Python Modules
Requires-Python: >=3.10
License-File: LICENSE
